dappier/__init__.py
dappier/dappier.py
dappier_py-0.2.0.dist-info/LICENSE
dappier_py-0.2.0.dist-info/METADATA
dappier_py-0.2.0.dist-info/WHEEL
dappier_py-0.2.0.dist-info/top_level.txt
dappier_py-0.2.0.dist-info/RECORD
